lakeshack/__init__.py
lakeshack/lakeshack.py
lakeshack/metastore.py
tests/__init__.py
tests/test_lakeshack.py
tests/test_metastore.py
tests/utils.py
lakeshack-0.2.3.dist-info/LICENSE
lakeshack-0.2.3.dist-info/METADATA
lakeshack-0.2.3.dist-info/WHEEL
lakeshack-0.2.3.dist-info/top_level.txt
lakeshack-0.2.3.dist-info/RECORD
