Metadata-Version: 2.1
Name: lakeshack
Version: 0.2.3
Summary: Query parquet files using pyarrow or S3 Select by first gathering file metadata into a database
Home-page: https://github.com/mhendrey/lakeshack
Author: Matthew Hendrey
Author-email: matthew.hendrey@gmail.com
License: GNU GPLv3
Project-URL: Source, https://github.com/mhendrey/lakeshack
Project-URL: Documentation, https://mhendrey.github.io/lakeshack
Keywords: pyarrow,s3,parquet
Classifier: Programming Language :: Python :: 3
Requires-Python: >=3.8
License-File: LICENSE
Requires-Dist: pyarrow >=8.0.0
Requires-Dist: sqlalchemy >=2.0.0
Requires-Dist: boto3
Requires-Dist: pandas
